MailAutoSent/Mail.py
MailAutoSent/__init__.py
MailAutoSent-0.2.dist-info/METADATA
MailAutoSent-0.2.dist-info/WHEEL
MailAutoSent-0.2.dist-info/top_level.txt
MailAutoSent-0.2.dist-info/RECORD
