Metadata-Version: 2.1
Name: MailAutoSent
Version: 0.2
Summary: Auto sent Mail
Home-page: https://github.com/GuangShuaiWang/MailAutoSent
Author: Wanggsh
Author-email: wanggsh98@qq.com
Requires-Dist: yagmail (==0.15.293)
